alarmpy/__init__.py
alarmpy/alarmpy.py
alarmpy/data/labels.json
alarmpy/tests/__init__.py
alarmpy/tests/test_alarmpy.py
alarmpy-1.5.4.dist-info/LICENSE
alarmpy-1.5.4.dist-info/METADATA
alarmpy-1.5.4.dist-info/WHEEL
alarmpy-1.5.4.dist-info/entry_points.txt
alarmpy-1.5.4.dist-info/top_level.txt
alarmpy-1.5.4.dist-info/RECORD
