Metadata-Version: 2.1
Name: alarmpy
Version: 1.5.4
Summary: Pikud Ha'oref Alarm Tracking
Home-page: https://github.com/yuvadm/alarmpy
Author: Yuval Adam
Author-email: _@yuv.al
License: GPLv3
Project-URL: Bug Tracker, https://github.com/yuvadm/alarmpy/issues
Classifier: Programming Language :: Python :: 3
Classifier: Development Status :: 5 - Production/Stable
Classifier: License :: OSI Approved :: GNU General Public License v3 (GPLv3)
Classifier: Operating System :: OS Independent
Classifier: Environment :: Console
Requires-Python: >=3.6
License-File: LICENSE
Requires-Dist: requests
Requires-Dist: click
Provides-Extra: mqttnotify
Requires-Dist: paho-mqtt ; extra == 'mqttnotify'
